<?xml version="1.0" encoding="utf-8"?><overlaydata><pois><poi type="tw_guides.tw_blkf.tw_blkf_icons.tw_blkf_icons_attack" mapid="364" xpos="666.607" ypos="39.3378" zpos="567.748" guid="x6BPTCYRNkW/yCqg5kPbvg==" /><poi type="tw_guides.tw_blkf.tw_blkf_icons.tw_blkf_icons_attack" mapid="364" xpos="720.035" ypos="41.9119" zpos="539.768" guid="iOygSeJN4Eqis10LywhdBQ==" /><poi type="tw_guides.tw_blkf.tw_blkf_icons.tw_blkf_icons_talk" mapid="364" xpos="589.565" ypos="40.034" zpos="532.161" guid="UdUa9TRq20WAAuq1AwkSIQ==" /><poi type="tw_guides.tw_blkf.tw_blkf_mission_start_signs.tw_blkf_mission_start_st09" mapid="364" xpos="535.614" ypos="50.2013" zpos="563.001" guid="GTpdX/3C3EawXo8dBQ847w==" /><poi type="tw_guides.tw_blkf.tw_blkf_mission_travel_teleports.tw_blkf_mission_travel_leave" mapid="364" xpos="727.98" ypos="41.531" zpos="534.819" guid="z7KW37/n/0iNRXHoYiDmdw==" /><trail type="tw_guides.tw_blkf.tw_blkf_mt_toggletrails.tw_blkf_mt09_1_toggletrail" guid="IQEOJ3zTHUOKZTNivBfJhQ==" fadenear="5000" fadefar="5100" traildata="Data/TW/BLKF/tw_blkf_mt09_1_toggletrail.trl" animspeed="0" texture="Data/TW/General/tw_trail_mc_griffon.png" mapid="364" /></pois></overlaydata>