<?xml version="1.0" encoding="utf-8"?><overlaydata><pois><poi type="tw_guides.tw_fractals.tw_fractals_uncategorized.tw_fractals_uncategorized_skip.tw_fractals_uncategorized_skip_aim" mapid="947" xpos="-838.927" ypos="846.289" zpos="-719.484" guid="u833YgU8AkWU9W9wk9V4Gg==" /><poi type="tw_guides.tw_fractals.tw_fractals_uncategorized.tw_fractals_uncategorized_skip.tw_fractals_uncategorized_skip_jump" mapid="947" xpos="-843.43" ypos="854.562" zpos="-709.608" guid="IoQeU/T9pUCxFwwOgLFmhw==" /><poi type="tw_guides.tw_fractals.tw_fractals_uncategorized.tw_fractals_uncategorized_skip.tw_fractals_uncategorized_skip_jump" mapid="947" xpos="-837.929" ypos="855.662" zpos="-711.442" guid="g9eWi7Z0DkmmWt0quEosiw==" /><poi type="tw_guides.tw_fractals.tw_fractals_uncategorized.tw_fractals_uncategorized_skip.tw_fractals_uncategorized_skip_slashgg" mapid="947" xpos="-830.988" ypos="858.121" zpos="-700.424" guid="900ux9Kh00a1MWB0GH0sgQ==" /><trail type="tw_guides.tw_fractals.tw_fractals_uncategorized.tw_fractals_uncategorized_skip.tw_fractals_uncategorized_skip_toggletrail" guid="s8JxMcRoCkClYu8izxOubA==" fadenear="5000" fadefar="5100" traildata="Data/TW/Fractals/tw_fractals_uncategorized_skip_toggletrail.trl" animspeed="0" texture="Data/TW/General/tw_trail_foot.png" mapid="947" /><poi type="tw_guides.tw_fractals.tw_fractals_undergroundfacility.tw_fractals_undergroundfacility_skip.tw_fractals_undergroundfacility_skip_stand" mapid="947" xpos="-825.284" ypos="843.709" zpos="-729.614" guid="5n4yhSUEWE661ATHhvUVjQ==" /><poi type="tw_guides.tw_fractals.tw_fractals_undergroundfacility.tw_fractals_undergroundfacility_skip.tw_fractals_undergroundfacility_skip_startsign" mapid="947" xpos="-806.952" ypos="833.58" zpos="-741.062" guid="G8fPbSiNeEOGxglbfQCJHw==" /></pois></overlaydata>